README.md
setup.py
example/__init__.py
example/visualizer_test.py
glimg/__init__.py
glimg/detbbox.py
glimg/math.py
glimg/transform.py
glimg/visualizer.py
glimg.egg-info/PKG-INFO
glimg.egg-info/SOURCES.txt
glimg.egg-info/dependency_links.txt
glimg.egg-info/top_level.txt