Metadata-Version: 2.1
Name: glimg
Version: 0.0.12
Summary: image processing tool for computer vision
Home-page: https://github.com/chencgln/glimg
Author: glchen
Author-email: chencglt@gmail.com
License: UNKNOWN
Platform: UNKNOWN
